[
  {
    "id": 1,
    "type": "misc",
    "title": "Smart House Simulator"
  },
  {
    "id": 2,
    "type": "game",
    "title": "Mandala Doily Maker"
  },
  {
    "id": 3,
    "type": "misc",
    "title": "BSc Project on Social Machines"
  },
  {
    "id": 4,
    "type": "game",
    "title": "Wendlessday"
  },
  {
    "id": 5,
    "type": "game",
    "title": "Scholastic Gymnastics"
  },
  {
    "id": 6,
    "type": "game",
    "title": "Firelight Playwrights"
  },
  {
    "id": 6,
    "type": "game",
    "title": "Paint By Numbers"
  },
  {
    "id": 6,
    "type": "game",
    "title": "Stranger Revolutions"
  },
  {
    "id": 6,
    "type": "game",
    "title": "Futhark Trinities"
  },
  {
    "id": 6,
    "type": "game",
    "title": "Parking Lot Exit"
  },
  {
    "id": 33,
    "type": "misc",
    "title": "MA Dissertation"
  }
]